maria_easy/__init__.py
maria_easy/connector.py
maria_easy/data_classes.py
tests/__init__.py
tests/maria-easy/__init__.py
tests/maria-easy/test_connector.py
tests/maria-easy/test_data_classes.py
maria_easy-0.0.1.dist-info/LICENSE
maria_easy-0.0.1.dist-info/METADATA
maria_easy-0.0.1.dist-info/WHEEL
maria_easy-0.0.1.dist-info/top_level.txt
maria_easy-0.0.1.dist-info/RECORD
