Metadata-Version: 2.1
Name: maria-easy
Version: 0.0.1
Summary: This python library is an easy way to use mariaDB.
Home-page: https://gitlab.com/oloc-forge/maria-easy.git
Author: Olivier Locard
Project-URL: Documentation, https://maria-easy.readthedocs.io/
Project-URL: Source, https://gitlab.com/oloc-forge/maria-easy.git
Keywords: mariadb development easy
Classifier: Intended Audience :: Developers
Classifier: Programming Language :: Python :: 3
Classifier: Programming Language :: Python :: 3.10
Classifier: License :: OSI Approved :: MIT License
License-File: LICENSE
